DiscoEPG/__init__.py
DiscoEPG/dataset_utils/__init__.py
DiscoEPG/dataset_utils/datagenerator.py
DiscoEPG/dataset_utils/datahelper.py
DiscoEPG/dataset_utils/dataloader.py
DiscoEPG/models/Dataset.py
DiscoEPG/models/Segmentation.py
DiscoEPG/models/SegmentationML.py
DiscoEPG/models/__init__.py
DiscoEPG/models/NN/CNN1D.py
DiscoEPG/models/NN/CNN2D.py
DiscoEPG/models/NN/MLP.py
DiscoEPG/models/NN/ResNet.py
DiscoEPG/models/NN/__init__.py
DiscoEPG/utils/__init__.py
DiscoEPG/utils/augmentation.py
DiscoEPG/utils/bash_utils.py
DiscoEPG/utils/configs_utils.py
DiscoEPG/utils/entropy.py
DiscoEPG/utils/metrics.py
DiscoEPG/utils/stats.py
DiscoEPG/utils/utils.py
DiscoEPG/utils/visualization.py
DiscoEPG/utils/PyTorchWavelets/__init__.py
DiscoEPG/utils/PyTorchWavelets/setup.py
DiscoEPG/utils/PyTorchWavelets/examples/__init__.py
DiscoEPG/utils/PyTorchWavelets/examples/benchmark.py
DiscoEPG/utils/PyTorchWavelets/examples/plot.py
DiscoEPG/utils/PyTorchWavelets/examples/plot_comparison.py
DiscoEPG/utils/PyTorchWavelets/examples/simple_example.py
DiscoEPG/utils/PyTorchWavelets/wavelets_pytorch/__init__.py
DiscoEPG/utils/PyTorchWavelets/wavelets_pytorch/network.py
DiscoEPG/utils/PyTorchWavelets/wavelets_pytorch/transform.py
DiscoEPG/utils/PyTorchWavelets/wavelets_pytorch/wavelets.py
DiscoEPG-0.0.23.dist-info/LICENSE
DiscoEPG-0.0.23.dist-info/METADATA
DiscoEPG-0.0.23.dist-info/WHEEL
DiscoEPG-0.0.23.dist-info/top_level.txt
DiscoEPG-0.0.23.dist-info/RECORD
