Metadata-Version: 2.1
Name: DiscoEPG
Version: 0.0.23
Summary: Open-source package for insects EPG data analysis
Home-page: https://github.com/HySonLab/ML4Insects
Author: DINHQuangDung1999
Author-email: dqdung999@gmail.com
License: MIT
Platform: UNKNOWN
Classifier: License :: OSI Approved :: MIT License
Classifier: Programming Language :: Python :: 3.10
Classifier: Operating System :: OS Independent
Requires-Python: >=3.10
License-File: LICENSE
Requires-Dist: PyWavelets
Requires-Dist: easydict
Requires-Dist: ipywidgets==8.1.3
Requires-Dist: librosa==0.10.2.post1
Requires-Dist: matplotlib==3.9.1
Requires-Dist: nbformat==5.10.4
Requires-Dist: numpy==1.26.4
Requires-Dist: opencv-python
Requires-Dist: pandas==2.2.2
Requires-Dist: plotly-resampler
Requires-Dist: plotly==5.22.0
Requires-Dist: pyts==0.13.0
Requires-Dist: scikit-learn==1.5.1
Requires-Dist: scipy==1.14.0
Requires-Dist: seaborn==0.13.2
Requires-Dist: torch==2.3.1
Requires-Dist: tqdm
Requires-Dist: xgboost==2.1.0
Requires-Dist: xlsxwriter
